[
    {
        "id" : 1,
        "titulo" : "Encuesta de Satisfaccion",
        "descripcion" : "Por favor, tómese un momento para responder a nuestras preguntas de satisfacción.",
        "preguntas" : [
            {
                "id" : 1,
                "pregunta" : "¿Cómo calificaría nuestro servicio?",
                "opciones" : [
                    {"id" : 1, "texto" : "Excelente" },
                    {"id" : 2, "texto" : "Bueno" },
                    {"id" : 3, "texto" : "Regular" },
                    {"id" : 4, "texto" : "Malo" }
                ]
            },
            {
                "id" : 2,
                "pregunta" : "¿Que podemos mejorar?",
                "opciones" : [
                    {"id" : 5, "texto" : "Atencion al cliente" },
                    {"id" : 6, "texto" : "Tiempo de entrega" },
                    {"id" : 7, "texto" : "Variedad de productos" },
                    {"id" : 8, "texto" : "Calidad de productos" }
                ]
            }
        ]
    },
    {
        "id" : 2,
        "titulo" : "Encuesta de Productos",
        "descripcion" : "Ayúdenos a mejorar nuestros productos completando esta encuesta.",
        "preguntas" : [
            {
                "id" : 3,
                "pregunta" : "¿Cual es su producto favorito?",
                "opciones" : [
                    {"id" : 9, "texto" : "Producto A" },
                    {"id" : 10, "texto" : "Producto B" },
                    {"id" : 11, "texto" : "Producto C" },
                    {"id" : 12, "texto" : "Producto D" }
                ]
            },
            {
                "id" : 2,
                "pregunta" : "¿Que podemos mejorar nuestro servicio al cliente?",
                "opciones" : [
                    {"id" : 13, "texto" : "Mayor disponibilidad de atencion" },
                    {"id" : 14, "texto" : "Mas opciones de contacto" },
                    {"id" : 15, "texto" : "Respuestas mas rapidas" },
                    {"id" : 16, "texto" : "Entrenamiento al personal" }
                ]
            }
        ]
    }
]